apm4py/__init__.py
apm4py/aggregation/__init__.py
apm4py/aggregation/core.py
apm4py/aggregation/groupings.py
apm4py/aggregation/metrics.py
apm4py/aggregation/utils.py
apm4py/api.py
apm4py/cli.py
apm4py/decorators.py
apm4py/event_log.py
apm4py/filter.py
apm4py/log_grower.py
apm4py/log_io.py
apm4py/log_manipulation.py
apm4py/logs.py
apm4py/process_mining_api.py
apm4py/resources.py
apm4py/structures.py
apm4py/utils.py
apm4py-0.1.14.dist-info/METADATA
apm4py-0.1.14.dist-info/WHEEL
apm4py-0.1.14.dist-info/entry_points.txt
apm4py-0.1.14.dist-info/RECORD
