Metadata-Version: 2.1
Name: apm4py
Version: 0.1.14
Summary: apm4py is a Python API for Appian Process Mining (APM)
Author: Appian
Requires-Python: >=3.10,<4.0
Classifier: Programming Language :: Python :: 3
Classifier: Programming Language :: Python :: 3.10
Classifier: Programming Language :: Python :: 3.11
Requires-Dist: pandas (>=2.0.3,<3.0.0)
Requires-Dist: polars (>=0.18.4,<0.19.0)
Requires-Dist: requests (>=2.31.0,<3.0.0)
Requires-Dist: tqdm (>=4.65.0,<5.0.0)
Requires-Dist: typer (>=0.9.0,<0.10.0)
